{
  "topic": "Yapay Zeka Haberleri",
  "created_at": "2026-07-10T05:39:37.134431+00:00",
  "period_days": 90,
  "videos_analyzed": 25,
  "niche_score": 28,
  "decision": "BEKLET: Talep zayıf veya başarı birkaç kanalda toplanmış.",
  "metrics": {
    "median_views": 51945,
    "median_views_per_day": 1344,
    "top_views_per_day": 60292,
    "channel_diversity": 0.84
  },
  "videos": [
    {
      "id": "B9300n7gLis",
      "title": "KORKUNÇ YAPAY ZEKA VERİTY EVİMİZE GELDİ ?! (bittik)",
      "channel": "Bora Kontaş",
      "published_at": "2026-06-30T15:30:06Z",
      "views": 578196,
      "views_per_day": 60292,
      "likes": 11551,
      "comments": 893,
      "duration_seconds": 1309,
      "url": "https://www.youtube.com/watch?v=B9300n7gLis"
    },
    {
      "id": "Hf-ZmONVwKs",
      "title": "TÜRKİYE'NİN YAPAY ZEKA PLANI",
      "channel": "Sadece ENES",
      "published_at": "2026-07-05T12:46:29Z",
      "views": 212522,
      "views_per_day": 45183,
      "likes": 8377,
      "comments": 930,
      "duration_seconds": 502,
      "url": "https://www.youtube.com/watch?v=Hf-ZmONVwKs"
    },
    {
      "id": "ttFuNAoYVaQ",
      "title": "Kalemine değil yapay zekaya güvendi - atv Ana Haber 26 Haziran 2026",
      "channel": "atv Haber",
      "published_at": "2026-06-26T16:48:04Z",
      "views": 191823,
      "views_per_day": 14172,
      "likes": 982,
      "comments": 336,
      "duration_seconds": 119,
      "url": "https://www.youtube.com/watch?v=ttFuNAoYVaQ"
    },
    {
      "id": "F5Sut5IsWnk",
      "title": "Kahramanmaraş’taki Okul Saldırısını Yapan Saldırganın Bıraktığı Kan Donduran Mektup... | A Haber",
      "channel": "A Haber",
      "published_at": "2026-04-18T17:35:29Z",
      "views": 741897,
      "views_per_day": 8992,
      "likes": 2678,
      "comments": 929,
      "duration_seconds": 291,
      "url": "https://www.youtube.com/watch?v=F5Sut5IsWnk"
    },
    {
      "id": "jsEY2_WkRZU",
      "title": "Yapay Zekâ İlk Kurşunu Attı: Bir AI Ajanı Gerçek Bir İnsana Saldırdı",
      "channel": "Bebar Bilim",
      "published_at": "2026-05-10T06:00:29Z",
      "views": 382733,
      "views_per_day": 6276,
      "likes": 15945,
      "comments": 1018,
      "duration_seconds": 646,
      "url": "https://www.youtube.com/watch?v=jsEY2_WkRZU"
    },
    {
      "id": "sz-NqnVijak",
      "title": "Yapay Zeka Vloggerı ile Tarihe Yolculuk! #cüneytözdemir #yapayzeka  #sondakika  #haber  #shorts",
      "channel": "Cüneyt Özdemir",
      "published_at": "2026-06-27T13:00:09Z",
      "views": 71024,
      "views_per_day": 5595,
      "likes": 922,
      "comments": 15,
      "duration_seconds": 85,
      "url": "https://www.youtube.com/watch?v=sz-NqnVijak"
    },
    {
      "id": "OvfZN_VrW6w",
      "title": "Maslak'ta Yapay Zekalı Vurgun: Avrupa'yı İstanbul'dan Dolandırdılar! Nihat Uludağ Detayları Aktardı",
      "channel": "CNN TÜRK",
      "published_at": "2026-07-04T14:00:11Z",
      "views": 22815,
      "views_per_day": 4036,
      "likes": 251,
      "comments": 80,
      "duration_seconds": 602,
      "url": "https://www.youtube.com/watch?v=OvfZN_VrW6w"
    },
    {
      "id": "_X7vw-1XKrU",
      "title": "RTX 5090'ı Bıraktım, Mac Studio'ya Geçtim: Yapay Zeka ile Uygulama Yaptım",
      "channel": "Mesut Çevik",
      "published_at": "2026-06-24T11:01:16Z",
      "views": 55162,
      "views_per_day": 3496,
      "likes": 2784,
      "comments": 398,
      "duration_seconds": 913,
      "url": "https://www.youtube.com/watch?v=_X7vw-1XKrU"
    },
    {
      "id": "AxTMAZ8R71U",
      "title": "KILIÇDAROĞLU'NUN HABERİ VAR MIYDI? MUTLAK BUTLAN İLE MHP İLİŞKİSİ...",
      "channel": "Cüneyt Özdemir",
      "published_at": "2026-05-21T10:14:54Z",
      "views": 141068,
      "views_per_day": 2832,
      "likes": 3537,
      "comments": 361,
      "duration_seconds": 4217,
      "url": "https://www.youtube.com/watch?v=AxTMAZ8R71U"
    },
    {
      "id": "zJ63xfgc3E0",
      "title": "🪳 Konya Selçuklu Versiyonu Hamam Böceği #hamamböceği #yapayzeka #konya #keşfet #komedi #fyp #shorts",
      "channel": "BÖCEK REİS",
      "published_at": "2026-06-24T15:23:41Z",
      "views": 41117,
      "views_per_day": 2637,
      "likes": 244,
      "comments": 16,
      "duration_seconds": 10,
      "url": "https://www.youtube.com/watch?v=zJ63xfgc3E0"
    },
    {
      "id": "4EQrzNUTYVs",
      "title": "Eski iPhone'lar için Siri'ye yapay zeka ekledim!",
      "channel": "ShiftDelete.Net",
      "published_at": "2026-06-24T09:00:16Z",
      "views": 36309,
      "views_per_day": 2289,
      "likes": 580,
      "comments": 34,
      "duration_seconds": 33,
      "url": "https://www.youtube.com/watch?v=4EQrzNUTYVs"
    },
    {
      "id": "8WazG58C4Sc",
      "title": "Google Agent Çağını Resmen Başlattı: I/O 2026",
      "channel": "Erhan Meydan",
      "published_at": "2026-05-29T16:05:57Z",
      "views": 82753,
      "views_per_day": 1991,
      "likes": 3039,
      "comments": 311,
      "duration_seconds": 1763,
      "url": "https://www.youtube.com/watch?v=8WazG58C4Sc"
    },
    {
      "id": "YV-rRYNi26o",
      "title": "ALEYNA TİLKİ'DEN ÇOK KONUŞULACAK \"YAPAY ZEKA\" İDDİASI #magazin",
      "channel": "Kaçamag TV",
      "published_at": "2026-06-01T13:45:05Z",
      "views": 51945,
      "views_per_day": 1344,
      "likes": 392,
      "comments": 51,
      "duration_seconds": 45,
      "url": "https://www.youtube.com/watch?v=YV-rRYNi26o"
    },
    {
      "id": "q-azA_lzPjQ",
      "title": "Yapay Zeka Şirketlerinden Korkutan Çağrı: Yapay Zekayı Durdurun!",
      "channel": "Kanal D Haber",
      "published_at": "2026-06-10T12:00:38Z",
      "views": 32174,
      "views_per_day": 1082,
      "likes": 324,
      "comments": 116,
      "duration_seconds": 107,
      "url": "https://www.youtube.com/watch?v=q-azA_lzPjQ"
    },
    {
      "id": "dNCqr7BvqjM",
      "title": "İsrail “sahte” dedi, görüntüsü çıktı - atv Ana Haber 14 Nisan 2026",
      "channel": "atv Haber",
      "published_at": "2026-04-14T16:46:05Z",
      "views": 83092,
      "views_per_day": 960,
      "likes": 517,
      "comments": 55,
      "duration_seconds": 109,
      "url": "https://www.youtube.com/watch?v=dNCqr7BvqjM"
    },
    {
      "id": "SIg457pWlME",
      "title": "Ebru Yaşar'dan flaş hamle! Yapay zeka önlemini böyle aldı #shortvideo #magazin #ebruyaşar #muzik #yt",
      "channel": "BionTV Magazin ",
      "published_at": "2026-05-15T12:08:07Z",
      "views": 46873,
      "views_per_day": 841,
      "likes": 137,
      "comments": 13,
      "duration_seconds": 43,
      "url": "https://www.youtube.com/watch?v=SIg457pWlME"
    },
    {
      "id": "K3SxIHFjYV0",
      "title": "Apple'dan iPhone kullanıcılarına tazminat kararı!",
      "channel": "Habertürk",
      "published_at": "2026-05-08T11:05:37Z",
      "views": 52237,
      "views_per_day": 832,
      "likes": 932,
      "comments": 18,
      "duration_seconds": 76,
      "url": "https://www.youtube.com/watch?v=K3SxIHFjYV0"
    },
    {
      "id": "W_qypgcnAZQ",
      "title": "Köye dönüşte yeni model: Maaşlı çiftçilik! | A Haber",
      "channel": "A Haber",
      "published_at": "2026-04-16T16:22:56Z",
      "views": 64324,
      "views_per_day": 761,
      "likes": 279,
      "comments": 11,
      "duration_seconds": 84,
      "url": "https://www.youtube.com/watch?v=W_qypgcnAZQ"
    },
    {
      "id": "U9l55Wy3HVY",
      "title": "Nikbinler Olayı Ne? Mustafa Sandal - Saygı1 Gecesinde Nikbinler Yapay Zeka Ve Playback Mi Kullandı?",
      "channel": "İKİNDİRİKS",
      "published_at": "2026-05-06T15:22:18Z",
      "views": 35056,
      "views_per_day": 543,
      "likes": 136,
      "comments": 79,
      "duration_seconds": 41,
      "url": "https://www.youtube.com/watch?v=U9l55Wy3HVY"
    },
    {
      "id": "onTvO8xnDS8",
      "title": "CNN Türk | Prof. Ali Murat Kırık | Ahmet Mümtaz Taylan ile Saliha Erdim'in kavgasındaki büyük tuzak!",
      "channel": "Ali Murat KIRIK",
      "published_at": "2026-05-28T20:12:58Z",
      "views": 19877,
      "views_per_day": 469,
      "likes": 72,
      "comments": 58,
      "duration_seconds": 133,
      "url": "https://www.youtube.com/watch?v=onTvO8xnDS8"
    },
    {
      "id": "uwPZmetHcX8",
      "title": "Yeni nesil telefon tuzağına dikkat  - atv Ana Haber 12 Mayıs 2026",
      "channel": "atv Haber",
      "published_at": "2026-05-12T20:08:01Z",
      "views": 25278,
      "views_per_day": 433,
      "likes": 238,
      "comments": 20,
      "duration_seconds": 182,
      "url": "https://www.youtube.com/watch?v=uwPZmetHcX8"
    },
    {
      "id": "hwxENbP5-4I",
      "title": "Korkutan Yapay Zeka Deneyi! - İnsan Müdahalesi Olmadan 15 Gün Geçiren Chatbotlar",
      "channel": "Çiçek ile Teknoloji",
      "published_at": "2026-05-26T07:00:11Z",
      "views": 18174,
      "views_per_day": 404,
      "likes": 820,
      "comments": 106,
      "duration_seconds": 1409,
      "url": "https://www.youtube.com/watch?v=hwxENbP5-4I"
    },
    {
      "id": "Q_XWeJV9M-M",
      "title": "Şarkıcı Mahsun Kırmızıgül’ün, yapay zeka ile müzik konusundaki bu sözlerine katılıyor musunuz?",
      "channel": "Selcuk YILDIZ",
      "published_at": "2026-04-20T19:42:40Z",
      "views": 31032,
      "views_per_day": 386,
      "likes": 455,
      "comments": 57,
      "duration_seconds": 135,
      "url": "https://www.youtube.com/watch?v=Q_XWeJV9M-M"
    },
    {
      "id": "2CGdQjlr4fE",
      "title": "MİT'ten Kritik Uyarı! Yapay Zekadaki Gizli Tehdidi Açıkladı - TGRT Haber",
      "channel": "TGRT Haber TV",
      "published_at": "2026-04-25T16:00:02Z",
      "views": 28101,
      "views_per_day": 372,
      "likes": 432,
      "comments": 59,
      "duration_seconds": 134,
      "url": "https://www.youtube.com/watch?v=2CGdQjlr4fE"
    },
    {
      "id": "LJjEmmT3KXU",
      "title": "10 Yapay Zeka Modelini Test Ettim! Hangisi En İyisi?",
      "channel": "Yusuf İpek",
      "published_at": "2026-04-11T09:26:16Z",
      "views": 29498,
      "views_per_day": 328,
      "likes": 1195,
      "comments": 208,
      "duration_seconds": 2568,
      "url": "https://www.youtube.com/watch?v=LJjEmmT3KXU"
    }
  ]
}