{
  "topic": "Sıfırdan Zirveye",
  "created_at": "2026-07-11T11:56:54.184084+00:00",
  "period_days": 90,
  "videos_analyzed": 25,
  "niche_score": 19,
  "decision": "BEKLET: Talep zayıf veya başarı birkaç kanalda toplanmış.",
  "metrics": {
    "median_views": 2874,
    "median_views_per_day": 108,
    "top_views_per_day": 20885,
    "channel_diversity": 0.6
  },
  "videos": [
    {
      "id": "qNWgeEDHkuM",
      "title": "YKS'de Sıfırdan Zirveye! YKS 2026'da Hedefini Yakalayan Meslek Liseli Kullanıcımız Anlatıyor!",
      "channel": "Doping Hafıza",
      "published_at": "2026-06-22T08:14:59Z",
      "views": 400037,
      "views_per_day": 20885,
      "likes": 3,
      "comments": 0,
      "duration_seconds": 31,
      "url": "https://www.youtube.com/watch?v=qNWgeEDHkuM"
    },
    {
      "id": "KDjwlDoPZ0c",
      "title": "99 gün kala zayıf öğrenci çağrıldı, tanrı gibi uyandı ve zirveye çıktı【Yoklama Saati】",
      "channel": "Sıfırdan Zirveye Mini Diziler",
      "published_at": "2026-07-01T11:00:06Z",
      "views": 21467,
      "views_per_day": 2138,
      "likes": 387,
      "comments": 11,
      "duration_seconds": 8441,
      "url": "https://www.youtube.com/watch?v=KDjwlDoPZ0c"
    },
    {
      "id": "HUg46gCpNQE",
      "title": "Gözleri röntgen gibi çalışıyor, yalan söyleyenin sonu kötü oldu!【Kazanma Modu Açıldı】",
      "channel": "Sıfırdan Zirveye Mini Diziler",
      "published_at": "2026-07-05T11:00:06Z",
      "views": 11760,
      "views_per_day": 1947,
      "likes": 256,
      "comments": 12,
      "duration_seconds": 8418,
      "url": "https://www.youtube.com/watch?v=HUg46gCpNQE"
    },
    {
      "id": "IF0nJdPfEiw",
      "title": "Sistem açıldı, eziklik bitti: Okul güzeli diz çöktü ama onu affetmedim!【Herkesin İstediği Adam】",
      "channel": "Sıfırdan Zirveye Mini Diziler",
      "published_at": "2026-06-29T11:00:06Z",
      "views": 16699,
      "views_per_day": 1387,
      "likes": 321,
      "comments": 9,
      "duration_seconds": 8926,
      "url": "https://www.youtube.com/watch?v=IF0nJdPfEiw"
    },
    {
      "id": "ZllbDcTXK6Y",
      "title": "1982’de yeniden doğdu… ailesi onu yok etmeye çalıştı ama o zirveye çıktı!【Zekânın Gücü】",
      "channel": "Sıfırdan Zirveye Mini Diziler",
      "published_at": "2026-07-02T11:00:06Z",
      "views": 9432,
      "views_per_day": 1043,
      "likes": 127,
      "comments": 2,
      "duration_seconds": 7393,
      "url": "https://www.youtube.com/watch?v=ZllbDcTXK6Y"
    },
    {
      "id": "jhf3n1B01tQ",
      "title": "13 Saniyede Tarih Yazdı: McGregor'ın Sıfırdan Zirveye Yolculuğu#ufc #mcgregor #mma #shorts #keşfet",
      "channel": "ZİFİR",
      "published_at": "2026-07-08T09:42:20Z",
      "views": 2671,
      "views_per_day": 863,
      "likes": 65,
      "comments": 0,
      "duration_seconds": 57,
      "url": "https://www.youtube.com/watch?v=jhf3n1B01tQ"
    },
    {
      "id": "nC6jjR1f33I",
      "title": "DST'NİN EN GÜÇLÜ KARAKTERİ Mİ? | Yeni WX-78 İle Sıfırdan Zirveye",
      "channel": "Uğur Dağ",
      "published_at": "2026-05-02T15:00:11Z",
      "views": 19781,
      "views_per_day": 283,
      "likes": 579,
      "comments": 159,
      "duration_seconds": 4754,
      "url": "https://www.youtube.com/watch?v=nC6jjR1f33I"
    },
    {
      "id": "m1ktH8O32ZY",
      "title": "SIFIRDAN ZİRVEYE - HİÇ PARA HARCAMADAN YENİ SERİ! - LAST DAY ON EARTH SURVİVAL - CANLI",
      "channel": "BURAK ABİ",
      "published_at": "2026-06-15T20:27:49Z",
      "views": 6327,
      "views_per_day": 247,
      "likes": 354,
      "comments": 46,
      "duration_seconds": 8261,
      "url": "https://www.youtube.com/watch?v=m1ktH8O32ZY"
    },
    {
      "id": "qV0-MHW1T30",
      "title": "\"Bu Araba Adamı ÜRKÜTÜYOR!\" - Nissan 350z  Sıfırdan Zirveye Giden Başarı Hikayesi",
      "channel": "Murat Bayat",
      "published_at": "2026-05-01T15:00:00Z",
      "views": 16803,
      "views_per_day": 237,
      "likes": 353,
      "comments": 67,
      "duration_seconds": 1821,
      "url": "https://www.youtube.com/watch?v=qV0-MHW1T30"
    },
    {
      "id": "4GosSb4OvtI",
      "title": "60 DAKİKA'DA 500.000$ KAZANDIM! SIFIRDAN ZİRVEYE 6.SEZON #1 | Car Parking Multiplayer1",
      "channel": "BarookiTv",
      "published_at": "2026-04-28T15:05:20Z",
      "views": 10082,
      "views_per_day": 136,
      "likes": 459,
      "comments": 31,
      "duration_seconds": 1212,
      "url": "https://www.youtube.com/watch?v=4GosSb4OvtI"
    },
    {
      "id": "0aqH9gh1B-M",
      "title": "DEĞERSİZ PETTEN EN DEĞERLİ PETE! 😱 SIFIRDAN ZİRVEYE PK XD TİCARETİ! | MAYA PK XD",
      "channel": "MAYA PK XD",
      "published_at": "2026-05-16T15:25:27Z",
      "views": 7127,
      "views_per_day": 128,
      "likes": 291,
      "comments": 65,
      "duration_seconds": 1079,
      "url": "https://www.youtube.com/watch?v=0aqH9gh1B-M"
    },
    {
      "id": "FKLwVrzovPM",
      "title": "ÖRSLEN 🔥 | Sıfırdan Zirveye Giden Yol (Motivasyon Klip)",
      "channel": "Hurrian AI",
      "published_at": "2026-04-20T16:00:33Z",
      "views": 9051,
      "views_per_day": 111,
      "likes": 13,
      "comments": 6,
      "duration_seconds": 150,
      "url": "https://www.youtube.com/watch?v=FKLwVrzovPM"
    },
    {
      "id": "6QoG6diY71Q",
      "title": "Kartezyen Çarpımı: Sıfırdan Zirveye + [2020-2025]  AYT Çıkmış Sorular | ÖSYM Ne Sordu?",
      "channel": "METİN HOCA MATEMATİK ",
      "published_at": "2026-06-14T20:39:14Z",
      "views": 2874,
      "views_per_day": 108,
      "likes": 186,
      "comments": 21,
      "duration_seconds": 979,
      "url": "https://www.youtube.com/watch?v=6QoG6diY71Q"
    },
    {
      "id": "vAcvysTdvTI",
      "title": "SIFIRDAN ZİRVEYE 3.BÖLÜM - HİÇ PARA HARCAMADAN YENİ SERİ! - LAST DAY ON EARTH SURVİVAL - CANLI",
      "channel": "BURAK ABİ",
      "published_at": "2026-06-18T08:21:37Z",
      "views": 2435,
      "views_per_day": 105,
      "likes": 143,
      "comments": 19,
      "duration_seconds": 5914,
      "url": "https://www.youtube.com/watch?v=vAcvysTdvTI"
    },
    {
      "id": "Rfri43HfKCE",
      "title": "SIFIRDAN ZİRVEYE 5.BÖLÜM - HİÇ PARA HARCAMADAN YENİ SERİ! - LAST DAY ON EARTH SURVİVAL - CANLI",
      "channel": "BURAK ABİ",
      "published_at": "2026-06-21T07:52:38Z",
      "views": 1742,
      "views_per_day": 86,
      "likes": 103,
      "comments": 3,
      "duration_seconds": 5593,
      "url": "https://www.youtube.com/watch?v=Rfri43HfKCE"
    },
    {
      "id": "ZAtlp0PEzG4",
      "title": "FC 26 Kariyer | Nhaga ile Sıfırdan Zirveye! (Yeni Sezon Başlıyor)",
      "channel": "Anıl Cömert",
      "published_at": "2026-04-24T13:01:14Z",
      "views": 4220,
      "views_per_day": 54,
      "likes": 179,
      "comments": 58,
      "duration_seconds": 1252,
      "url": "https://www.youtube.com/watch?v=ZAtlp0PEzG4"
    },
    {
      "id": "4G11UDm7W7s",
      "title": "10M BÜTÇE VERDİLER... SONUÇ HEPİMİZİ ŞAŞIRTTI! 😱🔥 | Sıfırdan Zirveye #40",
      "channel": "Oguzdesu",
      "published_at": "2026-05-30T19:43:16Z",
      "views": 2154,
      "views_per_day": 52,
      "likes": 65,
      "comments": 148,
      "duration_seconds": 1469,
      "url": "https://www.youtube.com/watch?v=4G11UDm7W7s"
    },
    {
      "id": "DXGTDAxtJaU",
      "title": "🔥 BİR DEVRİ KAPATTIK! HAVA KILICIYLA SON KEZ... 😱 | Sıfırdan Zirveye #45",
      "channel": "Oguzdesu",
      "published_at": "2026-06-11T19:00:03Z",
      "views": 1549,
      "views_per_day": 52,
      "likes": 33,
      "comments": 18,
      "duration_seconds": 1241,
      "url": "https://www.youtube.com/watch?v=DXGTDAxtJaU"
    },
    {
      "id": "wCNh9F9WHPM",
      "title": "ORGANİK TEPKİMELERİN ŞİFRESİ! 🗝️ | Tek Videoda Sıfırdan Zirveye (AYT Kimya)",
      "channel": "Ali Güven Kimya",
      "published_at": "2026-06-06T11:30:19Z",
      "views": 1100,
      "views_per_day": 31,
      "likes": 89,
      "comments": 22,
      "duration_seconds": 1644,
      "url": "https://www.youtube.com/watch?v=wCNh9F9WHPM"
    },
    {
      "id": "wK29aDvdsPk",
      "title": "Sıfırdan Zirveye! Rise Online Warrior Gelişim Serisi Bölüm 1: Ekipman Dizme",
      "channel": "VİSUALL",
      "published_at": "2026-05-13T16:01:35Z",
      "views": 1592,
      "views_per_day": 27,
      "likes": 39,
      "comments": 21,
      "duration_seconds": 1253,
      "url": "https://www.youtube.com/watch?v=wK29aDvdsPk"
    },
    {
      "id": "F3afuIX_RYw",
      "title": "YAVAŞ YAVAŞ CANAVARA DÖNÜŞÜYORUZ 😈🔥 | Sıfırdan Zirveye #38",
      "channel": "Oguzdesu",
      "published_at": "2026-05-19T19:00:32Z",
      "views": 1347,
      "views_per_day": 26,
      "likes": 65,
      "comments": 154,
      "duration_seconds": 1256,
      "url": "https://www.youtube.com/watch?v=F3afuIX_RYw"
    },
    {
      "id": "utV_-tIsg1o",
      "title": "BUGLU ZİNDAN MACERASI! 😅 SONUNDA ARADIĞIMIZ ITEM DÜŞTÜ 🔥 | Sıfırdan Zirveye #33",
      "channel": "Oguzdesu",
      "published_at": "2026-05-13T19:00:19Z",
      "views": 1145,
      "views_per_day": 20,
      "likes": 44,
      "comments": 49,
      "duration_seconds": 1755,
      "url": "https://www.youtube.com/watch?v=utV_-tIsg1o"
    },
    {
      "id": "9mbp1hfx2e8",
      "title": "YENİ ITEMLERLE GÜÇ PATLAMASI! 😱 ZİNDAN ÖNCESİ SON HAZIRLIK! 🔥 | Sıfırdan Zirveye #26",
      "channel": "Oguzdesu",
      "published_at": "2026-05-02T20:27:43Z",
      "views": 1338,
      "views_per_day": 19,
      "likes": 28,
      "comments": 21,
      "duration_seconds": 911,
      "url": "https://www.youtube.com/watch?v=9mbp1hfx2e8"
    },
    {
      "id": "uKXbQmU8coE",
      "title": "KULEDE ŞANS RESMEN ROLLERCOASTER GİBİYDİ 🎢🔥 | Sıfırdan Zirveye #32",
      "channel": "Oguzdesu",
      "published_at": "2026-05-10T19:00:32Z",
      "views": 1150,
      "views_per_day": 19,
      "likes": 27,
      "comments": 14,
      "duration_seconds": 1192,
      "url": "https://www.youtube.com/watch?v=uKXbQmU8coE"
    },
    {
      "id": "ekyQLyDvYEU",
      "title": "Benim Başarı Hikayem: Sıfırdan Zirveye Nasıl Yükseldim? | Orhan Tümerkan Tunçay",
      "channel": "Dedektif Orhan Tümerkan",
      "published_at": "2026-04-27T15:01:12Z",
      "views": 1128,
      "views_per_day": 15,
      "likes": 56,
      "comments": 15,
      "duration_seconds": 798,
      "url": "https://www.youtube.com/watch?v=ekyQLyDvYEU"
    }
  ]
}